Workbook

Sheet Assumptions
B1: 华晟精密 盈利预测模型 — 假设与驱动（Assumptions）
B2: 单位：万元（除增速、比率与每股收益外）；蓝色字体为可修改的输入假设
B4: 一、预测驱动假设（蓝色输入，可修改）
B5: 驱动假设 | C5: 2025E | D5: 2026E | E5: 2027E
B6: 营业收入增速 | C6: 0.15 | D6: 0.12 | E6: 0.1
B7: 归母净利率 | C7: 0.115 | D7: 0.118 | E7: 0.12
B8: 研发费用率（占营收） | C8: 0.168 | D8: 0.165 | E8: 0.16
B9: 经营现金流净额/营收 | C9: 0.128 | D9: 0.13 | E9: 0.132
B10: 总股本（万股，按 2024 年 EPS 反推） | C10: 6309.18
B12: 二、历史基准（2024A，取自年报 PDF，静态实际值）
B13: 2024 年营业收入（万元，脚注①剔除一次性处置收益） | C13: 53942
B14: 2024 年归母净利润（万元） | C14: 6183
B15: 2024 年研发投入（万元，脚注③全部费用化） | C15: 9051
B16: 2024 年经营活动现金流净额（万元） | C16: 6892
B17: 2024 年基本每股收益（元） | C17: 0.98
B19: Methodology: 预测期营收=上年营收×(1+营收增速)；归母净利=营收×归母净利率；研发投入=营收×研发费用率；经营现金流=营收×CFO率；EPS=归母净利/总股本。

Sheet 盈利预测
B1: 华晟精密 盈利预测（2022A–2027E）
B2: 单位：万元（除比率与每股收益）；历史 A 为实际值（黑字），预测 E 为公式；跨表引用绿字
B4: 指标 | C4: 2022A | D4: 2023A | E4: 2024A | F4: 2025E | G4: 2026E | H4: 2027E
B5: 营业收入（万元） | C5: 38417 | D5: 45166 | E5: 53942 | F5: =E5*(1+Assumptions!$C$6) | G5: =F5*(1+Assumptions!$D$6) | H5: =G5*(1+Assumptions!$E$6)
B6: 营收增速 | D6: =D5/C5-1 | E6: =E5/D5-1 | F6: =Assumptions!$C$6 | G6: =Assumptions!$D$6 | H6: =Assumptions!$E$6
B7: 归母净利润（万元） | C7: 3860 | D7: 4518 | E7: 6183 | F7: =F5*Assumptions!$C$7 | G7: =G5*Assumptions!$D$7 | H7: =H5*Assumptions!$E$7
B8: 归母净利率 | D8: =D7/D5 | E8: =E7/E5 | F8: =Assumptions!$C$7 | G8: =Assumptions!$D$7 | H8: =Assumptions!$E$7
B9: 研发投入（万元） | C9: 6120 | D9: 7483 | E9: 9051 | F9: =F5*Assumptions!$C$8 | G9: =G5*Assumptions!$D$8 | H9: =H5*Assumptions!$E$8
B10: 研发费用率 | D10: =D9/D5 | E10: =E9/E5 | F10: =Assumptions!$C$8 | G10: =Assumptions!$D$8 | H10: =Assumptions!$E$8
B11: 经营活动现金流净额（万元） | C11: 4204 | D11: 5377 | E11: 6892 | F11: =F5*Assumptions!$C$9 | G11: =G5*Assumptions!$D$9 | H11: =H5*Assumptions!$E$9
B12: CFO/营收 | D12: =D11/D5 | E12: =E11/E5 | F12: =Assumptions!$C$9 | G12: =Assumptions!$D$9 | H12: =Assumptions!$E$9
B13: 总股本（万股） | C13: =C7/C14 | D13: =D7/D14 | E13: =E7/E14 | F13: =Assumptions!$C$10 | G13: =Assumptions!$C$10 | H13: =Assumptions!$C$10
B14: 基本每股收益（元） | C14: 0.64 | D14: 0.73 | E14: 0.98 | F14: =F7/Assumptions!$C$10 | G14: =G7/Assumptions!$C$10 | H14: =H7/Assumptions!$C$10
B16: Sources: 历史数据取自《华晟精密2024年报节选.pdf》第2页主要财务数据（虚构公司，供测评）；预测假设见 Assumptions 表。

Sheet 敏感性分析
B1: 敏感性分析：2025E 营收增速假设 ±5pct 全链路联动
B2: 仅对 2025E 营收增速做 -5pct / 基准 / +5pct 情景，2026–2027 增速与各率维持基准；结果为全链路重算公式
B4: 情景 | C4: 悲观（-5pct） | D4: 基准 | E4: 乐观（+5pct）
B5: 2025E 营收增速 | C5: =Assumptions!$C$6-0.05 | D5: =Assumptions!$C$6+0 | E5: =Assumptions!$C$6+0.05
B6: 2025E 营业收入（万元） | C6: =盈利预测!$E$5*(1+C5) | D6: =盈利预测!$E$5*(1+D5) | E6: =盈利预测!$E$5*(1+E5)
B7: 2026E 营业收入（万元） | C7: =C6*(1+Assumptions!$D$6) | D7: =D6*(1+Assumptions!$D$6) | E7: =E6*(1+Assumptions!$D$6)
B8: 2027E 营业收入（万元） | C8: =C7*(1+Assumptions!$E$6) | D8: =D7*(1+Assumptions!$E$6) | E8: =E7*(1+Assumptions!$E$6)
B9: 2027E 归母净利润（万元） | C9: =C8*Assumptions!$E$7 | D9: =D8*Assumptions!$E$7 | E9: =E8*Assumptions!$E$7
B10: 2027E 基本 EPS（元） | C10: =C9/Assumptions!$C$10 | D10: =D9/Assumptions!$C$10 | E10: =E9/Assumptions!$C$10
B12: 说明：修改 Assumptions 表中的营收增速或净利率，本表三种情景全部联动重算；基准列（浅黄）与主模型结果一致。

Sheet 勾稽校验
B1: PDF 数据勾稽与跨页引用校验
B2: 单位：万元；差异=重算值-披露值，应为 0
B4: 一、分季度数据加总 vs 全年披露
B5: 校验项 | C5: Q1 | D5: Q2 | E5: Q3 | F5: Q4
B6: 分季度营收 | C6: 12104 | D6: 13566 | E6: 14220 | F6: 14052
B7: 分季度归母净利 | C7: 1302 | D7: 1494 | E7: 1683 | F7: 1704
B9: 二、研发投入构成（附注3，单位万元）
B10: 研发投入构成 | C10: 人员人工 | D10: 材料试制 | E10: 折旧摊销 | F10: 其他
C11: 4866 | D11: 2170 | E11: 1205 | F11: 810
B13: 三、勾稽差异（应为 0）
B14: 校验项 | C14: 重算值 | D14: 披露值 | E14: 差异
B15: 分季度营收合计 = 全年营收 | C15: =SUM(C6:F6) | D15: 53942 | E15: =C15-D15
B16: 分季度净利合计 = 全年归母净利 | C16: =SUM(C7:F7) | D16: 6183 | E16: =C16-D16
B17: 研发投入构成合计 = 披露研发投入 | C17: =SUM(C11:F11) | D17: 9051 | E17: =C17-D17
B19: 四、跨页引用
B20: 第1页脚注③ → 指向第2页「附注3：研发投入口径」（全部费用化、资本化率为0）。
B21: 脚注①：营业收入为剔除一次性处置收益后口径；脚注②：归母净利润为归属于上市公司股东的净利润。

Sheet 可比公司
B1: 可比公司对比（2024A，精密制造）
B2: 立讯精密/领益智造单位为亿元（真实公开数据）；华晟精密为虚构样本，由万元换算（÷10000）；派生指标为公式
B4: 指标 | C4: 立讯精密(002475) | D4: 领益智造(002600) | E4: 华晟精密(样本)
B5: 2023 营业收入（亿元） | C5: 2319.05 | D5: 341.24 | E5: 4.5166
B6: 2024 营业收入（亿元） | C6: 2687.95 | D6: 442.6 | E6: 5.3942
B7: 2023 归母净利润（亿元） | C7: 109.53 | D7: 20.51 | E7: 0.4518
B8: 2024 归母净利润（亿元） | C8: 133.66 | D8: 17.55 | E8: 0.6183
B9: 营业收入增速 | C9: =C6/C5-1 | D9: =D6/D5-1 | E9: =E6/E5-1
B10: 归母净利润增速 | C10: =C8/C7-1 | D10: =D8/D7-1 | E10: =E8/E7-1
B11: 2024 销售毛利率 | C11: 0.1041 | D11: 0.1577 | E11: 未披露
B12: 2024 归母净利率 | C12: =C8/C6 | D12: =D8/D6 | E12: =E8/E6
B13: 2024 研发费用（亿元） | C13: 85.56 | D13: 19.9 | E13: 0.9051
B14: 研发费用率 | C14: =C13/C6 | D14: =D13/D6 | E14: =E13/E6
B15: 2024 净资产收益率 ROE | C15: 0.1928 | D15: 0.0885 | E15: 未披露
B17: Sources: 立讯精密(002475)、领益智造(002600) 2023/2024 年报数据来自豆包金融数据（同花顺口径）；华晟精密为 PDF 虚构样本，毛利率、ROE 未在节选年报中披露。

Sheet 来源与口径
B1: 数据来源、口径与颜色约定
B4: 历史数据 | C4: 华晟精密2024年报节选.pdf（虚构公司，证券代码839201，披露日期2025-03-28），第2页主要财务数据，单位万元。
B5: 脚注① | C5: 营业收入为剔除一次性处置收益后的口径。
B6: 脚注② | C6: 归母净利润指归属于上市公司股东的净利润。
B7: 脚注③ / 跨页引用 | C7: 研发投入全部费用化、资本化率为0；第1页脚注③指向第2页「附注3：研发投入口径」。
B8: 分季度勾稽 | C8: 分季度营收合计 53,942 = 全年营收；分季度净利合计 6,183 = 全年归母净利；研发构成合计 9,051 = 研发投入。
B9: 可比公司 | C9: 立讯精密(002475)、领益智造(002600) 2023/2024 年报数据，来源豆包金融数据（同花顺利润业绩表口径），单位亿元。
B10: 预测假设 | C10: 2025–2027 营收增速、净利率、研发费用率、CFO率为测评演示假设（蓝色），非券商预测，可在 Assumptions 表修改。
B11: 颜色约定 | C11: 蓝色字体=可修改输入假设；黑色=历史实际值/本表公式；绿色=跨工作表引用；灰色斜体=说明注释。
